{
    "project_info": {
        "project_number": "823465219976",
        "project_id": "ludo-pets",
        "storage_bucket": "ludo-pets.firebasestorage.app"
    },
    "client": [
        {
            "client_info": {
                "mobilesdk_app_id": "1:823465219976:android:cd5b86d09b91269a5d8c3d",
                "android_client_info": {
                    "package_name": "com.ages.ludopets"
                }
            },
            "oauth_client": [],
            "api_key": [
                {
                    "current_key": "AIzaSyAFoi2BYgJB2YOeafkWz4g7_x71BYvFvKE"
                }
            ],
            "services": {
                "appinvite_service": {
                    "other_platform_oauth_client": []
                }
            }
        }
    ],
    "configuration_version": "1"
}
